xontrib/autovox.py
xontrib/vox.py
xontrib/voxapi.py
xontrib_vox-0.0.1.dist-info/LICENSE
xontrib_vox-0.0.1.dist-info/METADATA
xontrib_vox-0.0.1.dist-info/WHEEL
xontrib_vox-0.0.1.dist-info/top_level.txt
xontrib_vox-0.0.1.dist-info/RECORD
