Metadata-Version: 2.1
Name: xontrib-vox
Version: 0.0.1
Summary: Python virtual environment manager for xonsh.
Author-email: xontrib-vox <no@no.no>
License: MIT License
Project-URL: Homepage, https://github.com/xonsh/xontrib-vox
Project-URL: Documentation, https://github.com/xonsh/xontrib-vox/blob/master/README.md
Project-URL: Code, https://github.com/xonsh/xontrib-vox
Project-URL: Issue tracker, https://github.com/xonsh/xontrib-vox/issues
Platform: any
Classifier: Programming Language :: Python :: 3
Classifier: License :: OSI Approved :: MIT License
Classifier: Operating System :: OS Independent
Classifier: Topic :: System :: Shells
Classifier: Topic :: System :: System Shells
Classifier: Topic :: Terminals
Requires-Python: >=3.8
License-File: LICENSE
Requires-Dist: xonsh (>=0.12.5)
Provides-Extra: dev
Requires-Dist: pytest (>=7.0) ; extra == 'dev'
Requires-Dist: pytest-subprocess ; extra == 'dev'
